pyezliker
