Metadata-Version: 2.1
Name: pyezliker
Version: 1.0.2
Summary: Lib for crystalpy.
Home-page: https://github.com/shirosandev/pyEzLiker
Author-email: seraphineru@mail.ru
